odoo/addons/metadata/__init__.py
odoo/addons/metadata/__manifest__.py
odoo/addons/metadata/models/__init__.py
odoo/addons/metadata/models/metadata_line.py
odoo12_addon_metadata-12.0.0.1.0.dist-info/METADATA
odoo12_addon_metadata-12.0.0.1.0.dist-info/WHEEL
odoo12_addon_metadata-12.0.0.1.0.dist-info/top_level.txt
odoo12_addon_metadata-12.0.0.1.0.dist-info/RECORD
